thin_wrappers/db_utils.py
thin_wrappers/file_based_caching.py
thin_wrappers/grid_runner.py
thin_wrappers/session_based_caching.py
thin_wrappers/utils.py
thin_wrappers-0.4.12.dist-info/METADATA
thin_wrappers-0.4.12.dist-info/RECORD
thin_wrappers-0.4.12.dist-info/WHEEL
thin_wrappers-0.4.12.dist-info/top_level.txt
