Metadata-Version: 2.1
Name: thin-wrappers
Version: 0.4.12
Summary: Thin wrappers around common packages
Home-page: https://github.com/larssl780/thin_wrappers
Author: larssl780
Author-email: slick.stash.0m@icloud.com
License: MIT
Platform: UNKNOWN
Classifier: License :: OSI Approved :: MIT License
Classifier: Programming Language :: Python :: 3
Classifier: Programming Language :: Python :: 3.7
License-File: LICENSE
Requires-Dist: pickleshare
Requires-Dist: plotly
